{
  "DiziPal": "https://dizipal711.com", "InatBox": "https://inatbox.xyz", "Vavoo": "https://www1.vavoo.to",
  "FilmModu": "https://www.filmmodu.group", "FilmMakinesi": "https://filmmakinesi.pw", "HDFilmCehennemi": "https://www.hdfilmcehennemi.life",
  "FullHDFilmizlesene": "https://www.fullhdfilmizlesene.de", "JetFilmizle": "https://jetfilmizle.de", "720pIzle": "https://720pizle.org",
  "Dizilla": "https://dizilla.com", "Dizigom": "https://www.dizigom.tv", "DiziBox": "https://www.dizibox.tv",
  "Dizipub": "https://dizipub.tv", "YabanciDizi": "https://yabancidizi.co", "AnimeciX": "https://animecix.net",
  "Turkanime": "https://www.turkanime.tv", "AsyaFanatikleri": "https://asyafanatikleri.com", "Koreanturk": "https://www.koreanturk.com",
  "NeonSpor": "https://neonspor5.com", "GolgeTV": "https://golgetv.com", "RecTV": "https://rectv.com", "CanliTV": "https://canlitv.com",
  "BelgeselX": "https://belgeselx.com", "KultFilmler": "https://kultfilmler.com", "RareFilmm": "https://rarefilmm.com",
  "Webteizle": "https://webteizle.com", "Sinefy": "https://sinefy.com", "FilmGO": "https://filmgo.org", "Bicaps": "https://bicaps.net",
  "Lokum": "https://lokum.xyz", "Dizigun": "https://dizigun.tv", "Dizimob": "https://dizimob.org", "TurkSub": "https://turksub.com",
  "SineMutil": "https://sinemutil.com", "Filmkovasi": "https://filmkovasi.org", "Hdfilmizle": "https://hdfilmizle.be"
}
